discrete_math_helper/__init__.py
discrete_math_helper/calc.py
discrete_math_helper-1.1.3.dist-info/LICENSE
discrete_math_helper-1.1.3.dist-info/METADATA
discrete_math_helper-1.1.3.dist-info/WHEEL
discrete_math_helper-1.1.3.dist-info/top_level.txt
discrete_math_helper-1.1.3.dist-info/RECORD
