Metadata-Version: 2.1
Name: discrete-math-helper
Version: 1.1.3
Summary: Simple calculator for solving problems realted to discrete mathmatics, such as combinations, probabilities, truth-tables, and more.
Home-page: https://github.com/dokkharsh/discrete_math_helper
Author: Harsha Dokku
Author-email: dokkuh@umich.edu
Classifier: Programming Language :: Python :: 3
Classifier: License :: OSI Approved :: MIT License
Classifier: Operating System :: OS Independent
Requires-Python: >=3.7
License-File: LICENSE
